privateer/__about__.py
privateer/__init__.py
privateer/backup.py
privateer/check.py
privateer/cli.py
privateer/config.py
privateer/configure.py
privateer/keys.py
privateer/restore.py
privateer/schedule.py
privateer/server.py
privateer/service.py
privateer/tar.py
privateer/util.py
privateer/vault.py
privateer/yacron.py
privateer-2.1.1.dist-info/METADATA
privateer-2.1.1.dist-info/WHEEL
privateer-2.1.1.dist-info/entry_points.txt
privateer-2.1.1.dist-info/licenses/LICENSE.txt
privateer-2.1.1.dist-info/RECORD
