Metadata-Version: 2.4
Name: privateer
Version: 2.1.1
Summary: Tool to back up docker volumes onto remote machines
Project-URL: Documentation, https://github.com/reside-ic/privateer#readme
Project-URL: Issues, https://github.com/reside-ic/privateer/issues
Project-URL: Source, https://github.com/reside-ic/privateer
Author-email: Rich FitzJohn <r.fitzjohn@imperial.ac.uk>
License-Expression: MIT
License-File: LICENSE.txt
Classifier: Development Status :: 4 - Beta
Classifier: Programming Language :: Python
Classifier: Programming Language :: Python :: 3.10
Classifier: Programming Language :: Python :: 3.11
Classifier: Programming Language :: Python :: 3.12
Classifier: Programming Language :: Python :: 3.13
Classifier: Programming Language :: Python :: Implementation :: CPython
Classifier: Programming Language :: Python :: Implementation :: PyPy
Requires-Python: >=3.10
Requires-Dist: click
Requires-Dist: cryptography>=3.1
Requires-Dist: docker
Requires-Dist: docopt-ng
Requires-Dist: hvac
Requires-Dist: pydantic
Requires-Dist: tzlocal
Requires-Dist: yacron
